raugraf/__init__.py
raugraf/_version.py
raugraf/noderadius.py
raugraf/draft/__init__.py
raugraf/draft/minimizer_diversity.py
raugraf/draft/syntenic_anchors.py
raugraf-0.0.5.dist-info/LICENSE
raugraf-0.0.5.dist-info/METADATA
raugraf-0.0.5.dist-info/WHEEL
raugraf-0.0.5.dist-info/entry_points.txt
raugraf-0.0.5.dist-info/top_level.txt
raugraf-0.0.5.dist-info/RECORD
